semantify/__init__.py
semantify/interfaces.py
semantify/models.py
semantify/recommender/__init__.py
semantify/recommender/blog_recommender.py
semantify/run_tests.py
semantify/semantify.py
semantify/services/__init__.py
semantify/services/openai.py
semantify/services/sqlite.py
semantify/summarizer/__init__.py
semantify/summarizer/qa_generator.py
semantify/test_semantify.py
semantify/utils/__init__.py
semantify/utils/calculate_reading_time.py
semantify/utils/download_sqlite_extensions.py
semantify/utils/embedding_util.py
semantify/utils/frontmatter_utils.py
semantify-0.0.3.dist-info/LICENSE.txt
semantify-0.0.3.dist-info/METADATA
semantify-0.0.3.dist-info/WHEEL
semantify-0.0.3.dist-info/entry_points.txt
semantify-0.0.3.dist-info/RECORD
