Metadata-Version: 2.1
Name: semantify
Version: 0.0.3
Summary: Semantify enriches content with AI-generated summaries, Q&A, and semantically similar recommendations for CMS deployments.
Home-page: https://github.com/stephenc222/semantify
License: Apache 2.0
Author: Stephen Collins
Author-email: stephenc211@gmail.com
Requires-Python: >=3.9,<4.0
Classifier: License :: Other/Proprietary License
Classifier: Programming Language :: Python :: 3
Classifier: Programming Language :: Python :: 3.9
Classifier: Programming Language :: Python :: 3.10
Classifier: Programming Language :: Python :: 3.11
Classifier: Programming Language :: Python :: 3.12
Requires-Dist: openai (==1.6.1)
Requires-Dist: python-dotenv
Requires-Dist: pyyaml (==6.0.1)
Requires-Dist: requests
Requires-Dist: sqlean-py (>=3.45.1,<4.0.0)
Requires-Dist: torch (==2.2.0)
Requires-Dist: transformers (==4.37.2)
Requires-Dist: urllib3 (==1.26.7)
Project-URL: Repository, https://github.com/stephenc222/semantify
